Gravelamps.libs/libquadmath-f3c9c2d1.so.0.0.0
Gravelamps.libs/libgfortran-63e48404.so.5.0.0
Gravelamps.libs/libblas-b5dabdf8.so.3.11.0
Gravelamps.libs/libgomp-a61e2123.so.1.0.0
Gravelamps.libs/libntl-5ed3eec1.so.44.0.1
Gravelamps.libs/libflint-d412eade.so.17.0.0
Gravelamps.libs/libgmp-39898bd3.so.10.4.1
Gravelamps.libs/libgf2x-758154da.so.3.0.0
Gravelamps.libs/libarb-01f5af37.so.2.14.0
Gravelamps.libs/libcblas-7acc9f11.so.3.11.0
Gravelamps.libs/libmpfr-96f933b3.so.6.2.0
Gravelamps-2.3.dist-info/RECORD
Gravelamps-2.3.dist-info/top_level.txt
Gravelamps-2.3.dist-info/entry_points.txt
Gravelamps-2.3.dist-info/WHEEL
Gravelamps-2.3.dist-info/METADATA
Gravelamps-2.3.dist-info/LICENSE
gravelamps/inference.py
gravelamps/generate_lens.py
gravelamps/asimov.py
gravelamps/__init__.py
gravelamps/model/lib/libsis.so
gravelamps/model/lib/libpoint.so
gravelamps/model/lib/libnfw.so
gravelamps/model/lib/libmicropop.so
gravelamps/lensing/waveform_generator.py
gravelamps/lensing/unlensed.py
gravelamps/lensing/sis.py
gravelamps/lensing/point.py
gravelamps/lensing/o3point.py
gravelamps/lensing/nfw.py
gravelamps/lensing/millilensing.py
gravelamps/lensing/interpolator.py
gravelamps/lensing/generic.py
gravelamps/lensing/__init__.py
gravelamps/core/module_handling.py
gravelamps/core/graveparser.py
gravelamps/core/gravelog.py
gravelamps/core/file_handling.py
gravelamps/core/conversion.py
gravelamps/core/__init__.py
