Metadata-Version: 2.1
Name: Gravelamps
Version: 2.3
Summary: Software package designed for running template based analysis of lensedgravitational wave signals to determine the lens profile model. Builton top of the parameter estimation framework, Bilby, and arbitraryprecision library arb
Home-page: https://arxiv.org/abs/2112.07012
Download-URL: https://git.ligo.org/michael.wright/Gravelamps
Author: Mick Wright, Martin Hendry
Author-email: mick.wright@ligo.org
Maintainer: Mick Wright
License: MIT
Classifier: Programming Language :: Python :: 3
Classifier: Programming Language :: C++
Classifier: License :: OSI Approved :: MIT License
Requires-Python: >=3.8
License-File: LICENSE
Requires-Dist: asimov
Requires-Dist: astropy
Requires-Dist: bilby
Requires-Dist: bilby-pipe
Requires-Dist: htcondor
Requires-Dist: numpy
Requires-Dist: scipy
